WorldD/__init__.py
WorldD/__main__.py
WorldD/main.py
WorldD/options.toml
WorldD/profilling.py
WorldD/assets/icon-sheet.png
WorldD-1.0.1.dist-info/LICENSE
WorldD-1.0.1.dist-info/METADATA
WorldD-1.0.1.dist-info/WHEEL
WorldD-1.0.1.dist-info/top_level.txt
WorldD-1.0.1.dist-info/RECORD
