Metadata-Version: 2.1
Name: WorldD
Version: 1.0.1
Summary: Level editor made specifically for pygame games
Home-page: https://github.com/NotMEE12/WorldD
Author: Aleks Baran
Author-email: legominefan@gmail.com
Classifier: Programming Language :: Python :: 3
Classifier: License :: OSI Approved :: MIT License
Classifier: Operating System :: OS Independent
Requires: pygame
Requires: tomlkit
License-File: LICENSE
